volstats/__init__.py
volstats/close_to_close.py
volstats/ewma.py
volstats/garman_klass.py
volstats/gkyz.py
volstats/parkinson.py
volstats/rogers_satchell.py
volstats/rolling_helper.py
volstats/yang_zhang.py
volstats-0.1.1.dist-info/licenses/LICENSE
volstats-0.1.1.dist-info/METADATA
volstats-0.1.1.dist-info/WHEEL
volstats-0.1.1.dist-info/top_level.txt
volstats-0.1.1.dist-info/RECORD
